{"cameraMode":{"drawMode":0,"name":"Shaded","section":"Shading Mode"},"sceneLighting":true,"audioPlay":false,"sceneViewState":{"m_AlwaysRefresh":false,"showFog":true,"showSkybox":true,"showFlares":true,"showImageEffects":true,"showParticleSystems":true,"showVisualEffectGraphs":true,"m_FxEnabled":true},"in2DMode":false,"pivot":{"x":2.239563465118408,"y":-7.5492844581604,"z":2.083388328552246},"rotation":{"x":-0.482314795255661,"y":-0.018133709207177163,"z":0.009986549615859986,"w":-0.8757602572441101},"size":17.850465774536134,"orthographic":false}